{
  "hash": "00c24dd5",
  "configHash": "b6ec8411",
  "lockfileHash": "1ddefa68",
  "browserHash": "f7317fee",
  "optimized": {
    "react-dom/client": {
      "src": "../../node_modules/react-dom/client.js",
      "file": "react-dom_client.js",
      "fileHash": "434e97b7",
      "needsInterop": true
    },
    "react-router": {
      "src": "../../node_modules/react-router/dist/development/index.mjs",
      "file": "react-router.js",
      "fileHash": "be538ef8",
      "needsInterop": false
    },
    "react": {
      "src": "../../node_modules/react/index.js",
      "file": "react.js",
      "fileHash": "822c6bb6",
      "needsInterop": true
    },
    "react/jsx-dev-runtime": {
      "src": "../../node_modules/react/jsx-dev-runtime.js",
      "file": "react_jsx-dev-runtime.js",
      "fileHash": "363cca7a",
      "needsInterop": true
    }
  },
  "chunks": {
    "react-CoTh1R2n": {
      "file": "react-CoTh1R2n.js",
      "isDynamicEntry": false
    }
  }
}